LICENSE.md
MANIFEST.in
README.md
setup.cfg
setup.py
versioneer.py
pyenvbuilder/__init__.py
pyenvbuilder/_version.py
pyenvbuilder.egg-info/PKG-INFO
pyenvbuilder.egg-info/SOURCES.txt
pyenvbuilder.egg-info/dependency_links.txt
pyenvbuilder.egg-info/top_level.txt