Metadata-Version: 2.1
Name: pyenvbuilder
Version: 0.0.0
Summary: Python Environment Builder
Home-page: https://github.com/slaclab/pyenvbuilder
Author: SLAC National Accelerator Laboratory
License: BSD
Platform: UNKNOWN
Classifier: License :: OSI Approved :: BSD License
Classifier: Programming Language :: Python :: 2
Classifier: Programming Language :: Python :: 3
Classifier: Operating System :: OS Independent
